<?xml version="1.0" encoding="iso-8859-1"?>
<TRANSACTION xmlns:xsi="http://www.w3.org/2001/XMLSchema-instance" xmlns:xsd="http://www.w3.org/2001/XMLSchema">
  <Company>1</Company>
  <Date>180831</Date>
  <Time>2018-08-31 13:16:01</Time>
  <ORDERLINES>
    <ORDERLINE>
      <AssignmentTypeId>2</AssignmentTypeId>
      <OrderNo>2586386</OrderNo>
      <OrderlineNo>228</OrderlineNo>
      <ItemNo>12105010</ItemNo>
      <ItemDescription>Sexkantsskruv rostfri A4 M5x10</ItemDescription>
      <ReqQuantity>4</ReqQuantity>
      <Status>0</Status>
    </ORDERLINE>
  </ORDERLINES>
</TRANSACTION>