<?xml version="1.0" encoding="iso-8859-1"?>
<TRANSACTION xmlns:xsi="http://www.w3.org/2001/XMLSchema-instance" xmlns:xsd="http://www.w3.org/2001/XMLSchema">
  <Company>1</Company>
  <Date>180517</Date>
  <Time>2018-05-17 15:42:11</Time>
  <ORDERLINES>
    <ORDERLINE>
      <AssignmentTypeId>2</AssignmentTypeId>
      <OrderNo>18164</OrderNo>
      <OrderlineNo>100</OrderlineNo>
      <ItemNo>30020</ItemNo>
      <ItemDescription>AES CarboStar 375 20mm</ItemDescription>
      <ReqQuantity>2</ReqQuantity>
      <Status>0</Status>
    </ORDERLINE>
  </ORDERLINES>
</TRANSACTION>